strapi_client_enhanced/__init__.py
strapi_client_enhanced/py.typed
strapi_client_enhanced/strapi_client.py
strapi_client_enhanced/strapi_client_async.py
strapi_client_enhanced/strapi_client_base.py
strapi_client_enhanced/types.py
strapi_client_enhanced/utils.py
strapi_client_enhanced/models/__init__.py
strapi_client_enhanced/models/active_document.py
strapi_client_enhanced/models/api_parameters.py
strapi_client_enhanced/models/auth.py
strapi_client_enhanced/models/base_component.py
strapi_client_enhanced/models/base_document.py
strapi_client_enhanced/models/base_populatable.py
strapi_client_enhanced/models/file_payload.py
strapi_client_enhanced/models/media_image_document.py
strapi_client_enhanced/models/response.py
strapi_client_enhanced/models/single_smart_document.py
strapi_client_enhanced/models/smart_document.py
strapi_client_enhanced/models/smart_document_utils.py
strapi_client_enhanced/models/webhook_payload.py
strapi_client_enhanced-1.0.2.dist-info/METADATA
strapi_client_enhanced-1.0.2.dist-info/WHEEL
strapi_client_enhanced-1.0.2.dist-info/top_level.txt
strapi_client_enhanced-1.0.2.dist-info/RECORD
