Metadata-Version: 2.4
Name: strapi-client-enhanced
Version: 1.0.2
Summary: Interact with Strapi from Python using the REST API
Author-email: Just <zpzxgcr@gmail.com>
License: MIT
Project-URL: Homepage, https://github.com/zpzxgcr/strapi-client
Project-URL: Repository, https://github.com/zpzxgcr/strapi-client
Project-URL: Documentation, https://roslovets-inc.github.io/strapi-client/
Project-URL: Issues, https://github.com/zpzxgcr/strapi-client/issues
Project-URL: Changelog, https://github.com/zpzxgcr/strapi-client/blob/main/CHANGELOG.md
Keywords: strapi,cms,api,rest
Classifier: Development Status :: 4 - Beta
Classifier: Intended Audience :: Developers
Classifier: License :: OSI Approved :: MIT License
Classifier: Programming Language :: Python :: 3
Classifier: Programming Language :: Python :: 3.10
Classifier: Programming Language :: Python :: 3.11
Classifier: Programming Language :: Python :: 3.12
Classifier: Operating System :: OS Independent
Classifier: Topic :: Software Development :: Libraries :: Python Modules
Classifier: Topic :: Internet :: WWW/HTTP :: Dynamic Content
Requires-Python: >=3.10
Requires-Dist: httpx>=0.23.1
Requires-Dist: pydantic>=2.0
Requires-Dist: qs-codec>=1.1.5
